MANIFEST.in
README
pyucsm.py
setup.cfg
setup.py
ucsmquery.py
pyucsm.egg-info/PKG-INFO
pyucsm.egg-info/SOURCES.txt
pyucsm.egg-info/dependency_links.txt
pyucsm.egg-info/entry_points.txt
pyucsm.egg-info/top_level.txt