Metadata-Version: 1.0
Name: pyucsm
Version: 0.1.1a1
Summary: Client library for Cisco UCS XML API
Home-page: https://github.com/chemikadze/pyucsm
Author: Nikolay Sokolov
Author-email: nsokolov@griddynamics.com
License: Apache
Platform: UNKNOWN
Classifier: Development Status :: 3 - Alpha
Classifier: Environment :: Console
Classifier: Intended Audience :: Developers
Classifier: Intended Audience :: Information Technology
Classifier: License :: OSI Approved :: Apache Software License
Classifier: Operating System :: OS Independent
Classifier: Programming Language :: Python
